{
  "provisioningState": "Succeeded",
  "publicNetworkAccess": "Enabled",
  "tenantId": "67508d80-2b69-484e-ab62-ab263ca94733",
  "sku": {
    "name": "standard",
    "family": "A"
  },
  "enabledForTemplateDeployment": true,
  "enabledForDeployment": true,
  "enableRbacAuthorization": true,
  "enabledForDiskEncryption": true,
  "softDeleteRetentionInDays": 90,
  "accessPolicies": [],
  "enableSoftDelete": true,
  "enablePurgeProtection": true,
  "vaultUri": "https://d-awhsandbox-kv.vault.azure.net/"
}
