{
  "displayName": "Livsselskapet_FailedMailsLogicApp_Prod",
  "createdTime": "2025-03-24T15:00:16.6639278Z",
  "customParameterValues": {},
  "changedTime": "2025-06-11T21:00:00.5331725Z",
  "authenticatedUser": {},
  "connectionState": "Enabled",
  "overallStatus": "Connected",
  "testRequests": [],
  "testLinks": [],
  "statuses": [
    {
      "status": "Connected"
    }
  ],
  "parameterValueSet": {
    "name": "oauthServicePrincipal",
    "values": {
      "token:TenantId": {
        "value": "67508d80-2b69-484e-ab62-ab263ca94733"
      },
      "token:clientId": {
        "value": "541fd53c-2052-4176-95c3-5d985a02cfd6"
      }
    }
  },
  "api": {
    "name": "azuremonitorlogs",
    "type": "Microsoft.Web/locations/managedApis",
    "description": "Use this connector to query your Azure Monitor Logs across Log Analytics workspace and Application Insights component, to list or visualize results.",
    "id": "/subscriptions/996465bb-34d8-4c7d-99c1-bab3805301c8/providers/Microsoft.Web/locations/norwayeast/managedApis/azuremonitorlogs",
    "displayName": "Azure Monitor Logs",
    "category": "Standard",
    "brandColor": "#0072C6",
    "iconUri": "https://conn-afd-prod-endpoint-bmc9bqahasf3grgk.b01.azurefd.net/releases/v1.0.1702/1.0.1702.3810/azuremonitorlogs/icon.png"
  }
}
